{
  "+traits": [
    "legacyLaunch",
    "texturepacks",
    "legacyServices"
  ],
  "assetIndex": {
    "id": "pre-1.6",
    "sha1": "7d85a08c105d9b38491a4d7aa2a078761f8c6d7d",
    "size": 178730,
    "totalSize": 49381897,
    "path": "bafkreie5jv4zrithabsepiwicshqpu3jy5kiaypcguy2mrjtgsyb3mkjri"
  },
  "compatibleJavaMajors": [
    8
  ],
  "formatVersion": 1,
  "mainJar": {
    "downloads": {
      "artifact": {
        "sha1": "a8403c0d4c0cdb65722d864d9cf42663b8aab08b",
        "size": 3934973,
        "path": "bafybeifxiw526l5k7qwqmreb5wa76umzps5ptvq52rpaofdebwuodwt4ye/client.jar"
      }
    },
    "name": "com.mojang:minecraft:12w06a:client"
  },
  "name": "Minecraft",
  "order": -2,
  "releaseTime": "2012-02-09T00:00:00+02:00",
  "requires": [
    {
      "suggests": "2.9.4-nightly-20150209",
      "uid": "org.lwjgl"
    }
  ],
  "type": "old_snapshot",
  "uid": "net.minecraft",
  "version": "12w06a"
}